README.md
setup.py
yocrypt/__init__.py
yocrypt/decode.py
yocrypt/encode.py
yocrypt.egg-info/PKG-INFO
yocrypt.egg-info/SOURCES.txt
yocrypt.egg-info/dependency_links.txt
yocrypt.egg-info/top_level.txt