Metadata-Version: 2.1
Name: yocrypt
Version: 1.0.0
Summary: YoCrypt is a new way to encode and decode text symetrically.
Home-page: https://github.com/PetitPotiron/YoCrypt
Author: PetitPotiron
License: MIT License
Platform: UNKNOWN
